meditor/__init__.py
meditor/__main__.py
meditor/meditor.py
pypanelx/__init__.py
pypanelx/__main__.py
pypanelx/pypanelx.py
pypanelx-1.0.3.data/data/lib/site-packages/meditor/dist/meditor-1.0.0.exe
pypanelxsworker/__init__.py
pypanelxsworker/__main__.py
pypanelxsworker/serviceworker.py
tools/__init__.py
tools/iltools.py
pypanelx-1.0.3.dist-info/LICENSE
pypanelx-1.0.3.dist-info/METADATA
pypanelx-1.0.3.dist-info/WHEEL
pypanelx-1.0.3.dist-info/entry_points.txt
pypanelx-1.0.3.dist-info/top_level.txt
pypanelx-1.0.3.dist-info/RECORD
