Metadata-Version: 2.1
Name: pypanelx
Version: 1.0.3
Summary: A full Python Panel CLI
Author: James Phoenix
Author-email: sierra117autumn@gmail.com
Requires-Python: >=3.9
License-File: LICENSE
Requires-Dist: instaloader
Requires-Dist: flask
